Metadata-Version: 1.1
Name: treeop
Version: 0.0.1
Summary: collection of operations for nested dict, list and tuple.
Home-page: https://github.com/kktk-KO/treeop
Author: kktk
Author-email: kktkko3579@gmail.com
License: CC0
Keywords: python list dict tuple
Platform: UNKNOWN
Classifier: Development Status :: 3 - Alpha
Classifier: Intended Audience :: Developers
Classifier: License :: CC0 1.0 Universal (CC0 1.0) Public Domain Dedication
Classifier: Programming Language :: Python :: 2
Classifier: Programming Language :: Python :: 3
